README.txt
setup.cfg
setup.py
Products/__init__.py
Products.fatsyndication.egg-info/PKG-INFO
Products.fatsyndication.egg-info/SOURCES.txt
Products.fatsyndication.egg-info/dependency_links.txt
Products.fatsyndication.egg-info/entry_points.txt
Products.fatsyndication.egg-info/namespace_packages.txt
Products.fatsyndication.egg-info/not-zip-safe
Products.fatsyndication.egg-info/requires.txt
Products.fatsyndication.egg-info/top_level.txt
Products/fatsyndication/IGNORE.txt
Products/fatsyndication/README.txt
Products/fatsyndication/__init__.py
Products/fatsyndication/config.py
Products/fatsyndication/configure.zcml
Products/fatsyndication/permissions.py
Products/fatsyndication/tests.py
Products/fatsyndication/version.txt
Products/fatsyndication/adapters/__init__.py
Products/fatsyndication/adapters/feed.py
Products/fatsyndication/adapters/feedentry.py
Products/fatsyndication/adapters/feedsource.py
Products/fatsyndication/browser/__init__.py
Products/fatsyndication/browser/feed.py
Products/fatsyndication/profiles/default/metadata.xml
Products/fatsyndication/profiles/default/skins.xml
Products/fatsyndication/skins/fatsyndication/atom.css.dtml
Products/fatsyndication/skins/fatsyndication/atom_feed.gif
Products/fatsyndication/skins/fatsyndication/rdf_feed.gif
Products/fatsyndication/skins/fatsyndication/rss_feed.gif
docs/HISTORY.txt
docs/INSTALL.txt
docs/LICENSE.GPL
docs/LICENSE.txt