Metadata-Version: 1.0
Name: Products.fatsyndication
Version: 1.0.0
Summary: Archetypes implementation for basesyndication
Home-page: http://dev.plone.org/collective/browser/Products.fatsyndication
Author: Tim Hicks
Author-email: tim@sitefusion.co.uk
License: GPL
Keywords: syndication atom rss plone
Platform: UNKNOWN
Classifier: Framework :: Plone
Classifier: Framework :: Zope2
Classifier: Framework :: Zope3
Classifier: Programming Language :: Python
Classifier: Topic :: Software Development :: Libraries :: Python Modules
